{
  "name": "Umesh Kumar K",
  "photoUrl": "uk-logo-circle.png",
  "intro": "19+ years web architect specializing in legacy modernization and Enterprise grade GenAI integrations.",
  "introHtml": "19+ years web architect specializing in legacy modernization and Eterprise grade GenAI integrations.",
  "webpageTitle": "Umesh Kumar K | Architect | Front End | GenAI integration",
  "webpageDescription": "19+ years web architect specializing in legacy modernization and Enterprise grade GenAI integrations.",
  "resumeUrl": "https://example-files.online-convert.com/document/pdf/example.pdf",

  "_comment": "Add your social links below. Leave the 'url' empty to hide the icon. Set 'showInContact' to true or false to control if it appears in the Contact section.",
  "socials": [
    {
      "name": "GitHub",
      "url": "https://github.com/umesh-kumar-k",
      "icon": "mdi:github",
      "showInContact": true
    },
    {
      "name": "LinkedIn",
      "url": "https://linkedin.com/in/umesh-kumar-k-b116011a7",
      "icon": "mdi:linkedin",
      "showInContact": true
    },
    {
      "name": "Email",
      "url": "mailto:umeshkumar.k@yahoo.com",
      "icon": "mdi:email",
      "showInContact": true
    },
    {
      "name": "Whatsapp",
      "url": "https://wa.me/919945734568",
      "icon": "mdi:whatsapp",
      "showInContact": true
    }
  ]
}